hdwallet/__init__.py
hdwallet/cryptocurrencies.py
hdwallet/derivations.py
hdwallet/exceptions.py
hdwallet/hdwallet.py
hdwallet/symbols.py
hdwallet/utils.py
hdwallet/version.py
hdwallet/cli/__init__.py
hdwallet/cli/__main__.py
hdwallet/cli/generate/__init__.py
hdwallet/cli/generate/addresses.py
hdwallet/cli/generate/hdwallet.py
hdwallet/cli/list/__init__.py
hdwallet/cli/list/cryptocurrencies.py
hdwallet/cli/list/languages.py
hdwallet/cli/list/strengths.py
hdwallet/libs/__init__.py
hdwallet/libs/base58.py
hdwallet/libs/bech32.py
hdwallet/libs/ecc.py
hdwallet/libs/ripemd160.py
tests/__init__.py
tests/conftest.py
tests/test_base58.py
tests/test_derivations.py
tests/test_exceptions.py
tests/test_symbols.py
tests/test_utils.py
tests/cli/__init__.py
tests/cli/test_cli.py
tests/cli/generate/__init__.py
tests/cli/generate/test_addresses.py
tests/cli/generate/test_hdwallet.py
tests/cli/list/__init__.py
tests/cli/list/test_cryptocurrencies.py
tests/cli/list/test_languages.py
tests/cli/list/test_strengths.py
tests/hdwallet/__init__.py
tests/hdwallet/test_from_entropy.py
tests/hdwallet/test_from_mnemonic.py
tests/hdwallet/test_from_private_key.py
tests/hdwallet/test_from_public_key.py
tests/hdwallet/test_from_seed.py
tests/hdwallet/test_from_wif.py
tests/hdwallet/test_from_xprivate_key.py
tests/hdwallet/test_from_xpublic_key.py
hdwallet_slip39-2.3.0.dist-info/LICENSE
hdwallet_slip39-2.3.0.dist-info/METADATA
hdwallet_slip39-2.3.0.dist-info/WHEEL
hdwallet_slip39-2.3.0.dist-info/entry_points.txt
hdwallet_slip39-2.3.0.dist-info/top_level.txt
hdwallet_slip39-2.3.0.dist-info/RECORD
