Metadata-Version: 2.1
Name: hdwallet-slip39
Version: 2.3.0
Summary: Python-based library for the implementation of a hierarchical deterministic wallet generator for more than 140+ multiple cryptocurrencies.
Home-page: https://github.com/pjkundert/python-hdwallet
Author: Meheret Tesfaye Batu
Author-email: meherett.batu@gmail.com
License: MIT
Project-URL: Tracker, https://github.com/meherett/python-hdwallet/issues
Project-URL: Documentation, https://hdwallet.readthedocs.io
Keywords: cryptography,cli,wallet,bip32,bip44,bip39,hdwallet,cryptocurrencies,bitcoin,ethereum
Classifier: Development Status :: 5 - Production/Stable
Classifier: License :: OSI Approved :: ISC License (ISCL)
Classifier: Programming Language :: Python :: 3.8
Classifier: Programming Language :: Python :: 3.9
Classifier: Programming Language :: Python :: 3.10
Classifier: Programming Language :: Python :: 3.11
Classifier: Programming Language :: Python :: 3.12
Classifier: Programming Language :: Python :: 3.13
Classifier: Topic :: Software Development :: Libraries :: Python Modules
Requires-Python: >=3.6,<4
License-File: LICENSE
Requires-Dist: ecdsa <1,>=0.19.0
Requires-Dist: mnemonic <1,>=0.21
Requires-Dist: pycryptodome <4,>=3.21
Requires-Dist: base58 <3,>=2.1.1
Provides-Extra: cli
Requires-Dist: click <9,>=8.1.3 ; extra == 'cli'
Requires-Dist: click-aliases <2,>=1.0.1 ; extra == 'cli'
Requires-Dist: tabulate <1,>=0.9.0 ; extra == 'cli'
Provides-Extra: docs
Requires-Dist: sphinx <6,>=5.3.0 ; extra == 'docs'
Requires-Dist: furo ==2022.12.7 ; extra == 'docs'
Requires-Dist: sphinx-click <5,>=4.4.0 ; extra == 'docs'
Provides-Extra: tests
Requires-Dist: pytest <8,>=7.2.0 ; extra == 'tests'
Requires-Dist: pytest-cov <5,>=4.0.0 ; extra == 'tests'
Requires-Dist: tox ==3.28.0 ; extra == 'tests'
